Metadata-Version: 2.1
Name: CrackedAuth
Version: 1.0
Summary: Auth for CIO
Home-page: 
Author: Beete
Author-email: beete@protonmail.com
License: MIT
Keywords: crackedauth
